GOLPixel.v
module GOLPixel(out, a, b, c, d, e, f, g, h);

	output wire out;
	input wire a, b, c, d, e, f, g, h;
	
	not notA(nA, a);
	not notB(nB, b);
	not notC(nC, c);
	not notD(nD, d);
	not notE(nE, e);
	not notF(nF, f);
	not notG(nG, g);
	not notH(nH, h);
	
	and and0(out0, nA, nB, nC, nD, nE, g, h);
	and and1(out1, nA, nB, nC, nD, f, nG, h);
	and and2(out2, nA, nB, nC, nD, f, g, nH);
	and and3(out3, nA, nB, nC, nD, e, nF, h);
	and and4(out4, nA, nB, nC, e, nF, g, nH);
	and and5(out5, nA, nB, nC, e, f, nG, nH);
	and and6(out6, nA, nB, nC, d, nE, nF, h);
	and and7(out7, nA, nB, nC, d, nE, g, nH);
	and and8(out8, nA, nB, nC, d, nE, f, nG);
	and and9(out9, nA, nB, nC, d, e, nF, nG);
	and and10(out10, nA, nB, c, nD, nE, nF, h);
	and and11(out11, nA, nB, c, nD, nE, g, nH);
	and and12(out12, nA, nB, c, nD, nE, f, nG);
	and and13(out13, nA, nB, c, nD, e, nF, nG);
	and and14(out14, nA, nB, c, d, nE, nF, nG);
	and and15(out15, nA, b, nC, nD, nE, nF, h);
	and and16(out16, nA, b, nC, nD, nE, g, nH);
	and and17(out17, nA, b, nC, nD, nE, f, nG);
	and and18(out18, nA, b, nC, nD, e, nF, nG);
	and and19(out19, nA, b, nC, d, nE, nF, nG);
	and and20(out20, nA, b, c, nD, nE, nF, nG);
	and and21(out21, a, nB, nC, nD, nE, nF, h);
	and and22(out22, a, nB, nC, nD, nE, g, nH);
	and and23(out23, a, nB, nC, nD, nE, f, nG);
	and and24(out24, a, nB, nC, nD, e, nF, nG);
	and and25(out25, a, nB, nC, d, nE, nF, nG);
	and and26(out26, a, nB, c, nD, nE, nF, nG);
	and and27(out27, a, b, nC, nD, nE, nF, nG);
	and and28(out28, nA, nB, nD, e, nF, g, nH);
	and and29(out29, nA, nC, nD, e, nF, g, nH);
	and and30(out30, nB, nC, nD, e, nF, g, nH);
	and and31(out31, nA, nB, nD, e, f, nG, nH);
	and and32(out32, nA, nC, nD, e, f, nG, nH);
	and and33(out33, nB, nC, nD, e, f, nG, nH);
	and and34(out34, nA, nB, d, nE, nF, g, nH);
	and and35(out35, nA, nC, d, nE, nF, g, nH);
	and and36(out36, nB, nC, d, nE, nF, g, nH);
	and and37(out37, nA, nB, d, nE, f, nG, nH);
	and and38(out38, nA, nC, d, nE, f, nG, nH);
	and and39(out39, nB, nC, d, nE, f, nG, nH);
	and and40(out40, nA, nB, d, e, nF, nG, nH);
	and and41(out41, nA, nC, d, e, nF, nG, nH);
	and and42(out42, nB, nC, d, e, nF, nG, nH);
	and and43(out43, nA, c, nD, nE, nF, g, nH);
	and and44(out44, nB, c, nD, nE, nF, g, nH);
	and and45(out45, nA, c, nD, nE, f, nG, nH);
	and and46(out46, nB, c, nD, nE, f, nG, nH);
	and and47(out47, nA, c, nD, e, nF, nG, nH);
	and and48(out48, nB, c, nD, e, nF, nG, nH);
	and and49(out49, nA, c, d, nE, nF, nG, nH);
	and and50(out50, nB, c, d, nE, nF, nG, nH);
	and and51(out51, b, nC, nD, nE, nF, g, nH);
	and and52(out52, b, nC, nD, nE, f, nG, nH);
	and and53(out53, b, nC, nD, e, nF, nG, nH);
	and and54(out54, b, nC, d, nE, nF, nG, nH);
	and and55(out55, b, c, nD, nE, nF, nG, nH);

	or or0(out, out0, out1, out2, out3, out4, out5, out6, out7, 
	out8, out9, out10, out11, out12, out13, out14, out15, 
	out16, out17, out18, out19, out20, out21, out22, out23, 
	out24, out25, out26, out27, out28, out29, out30, out31, 
	out32, out33, out34, out35, out36, out37, out38, out39, 
	out40, out41, out42, out43, out44, out45, out46, out47, 
	out48, out49, out50, out51, out52, out53, out54, out55);

	
endmodule

GOLPixelTest.v
`include "GOLPixel.v"

module TestBench;

	GOLPixel pixel(out, a, b, c, d, e, f, g, h);
	Tester myTester(a, b, c, d, e, f, g, h, out);

	wire out;
	wire a, b, c, d, e, f, g, h;

	initial
	begin
		$dumpfile("pixel.vcd");
		$dumpvars(1,pixel);
	end

endmodule

module Tester(a, b, c, d, e, f, g, h, out);
	output wire a, b, c, d, e, f, g, h;
	input wire out;
	
	reg[7:0] outreg;
	
	reg[7:0] i;
	
	assign a = outreg[0];
	assign b = outreg[1];
	assign c = outreg[2];
	assign d = outreg[3];
	assign e = outreg[4];
	assign f = outreg[5];
	assign g = outreg[6];
	assign h = outreg[7];
	
	parameter delay = 20;
	
	initial
	begin
		outreg = 8'd0;
		i = 8'd0;
	end
	
	always
	begin
	repeat(255) begin
		#delay outreg = i;
		i = i+1;
	end
	$finish;
	end
endmodule

pixel.vcd
$date
	Tue Nov 20 14:29:33 2012
$end
$version
	Icarus Verilog
$end
$timescale
	1s
$end
$scope module TestBench $end
$scope module pixel $end
$var wire 1 ! a $end
$var wire 1 " b $end
$var wire 1 # c $end
$var wire 1 $ d $end
$var wire 1 % e $end
$var wire 1 & f $end
$var wire 1 ' g $end
$var wire 1 ( h $end
$var wire 1 ) nA $end
$var wire 1 * nB $end
$var wire 1 + nC $end
$var wire 1 , nD $end
$var wire 1 - nE $end
$var wire 1 . nF $end
$var wire 1 / nG $end
$var wire 1 0 nH $end
$var wire 1 1 out $end
$var wire 1 2 out0 $end
$var wire 1 3 out1 $end
$var wire 1 4 out10 $end
$var wire 1 5 out11 $end
$var wire 1 6 out12 $end
$var wire 1 7 out13 $end
$var wire 1 8 out14 $end
$var wire 1 9 out15 $end
$var wire 1 : out16 $end
$var wire 1 ; out17 $end
$var wire 1 < out18 $end
$var wire 1 = out19 $end
$var wire 1 > out2 $end
$var wire 1 ? out20 $end
$var wire 1 @ out21 $end
$var wire 1 A out22 $end
$var wire 1 B out23 $end
$var wire 1 C out24 $end
$var wire 1 D out25 $end
$var wire 1 E out26 $end
$var wire 1 F out27 $end
$var wire 1 G out28 $end
$var wire 1 H out29 $end
$var wire 1 I out3 $end
$var wire 1 J out30 $end
$var wire 1 K out31 $end
$var wire 1 L out32 $end
$var wire 1 M out33 $end
$var wire 1 N out34 $end
$var wire 1 O out35 $end
$var wire 1 P out36 $end
$var wire 1 Q out37 $end
$var wire 1 R out38 $end
$var wire 1 S out39 $end
$var wire 1 T out4 $end
$var wire 1 U out40 $end
$var wire 1 V out41 $end
$var wire 1 W out42 $end
$var wire 1 X out43 $end
$var wire 1 Y out44 $end
$var wire 1 Z out45 $end
$var wire 1 [ out46 $end
$var wire 1 \ out47 $end
$var wire 1 ] out48 $end
$var wire 1 ^ out49 $end
$var wire 1 _ out5 $end
$var wire 1 ` out50 $end
$var wire 1 a out51 $end
$var wire 1 b out52 $end
$var wire 1 c out53 $end
$var wire 1 d out54 $end
$var wire 1 e out55 $end
$var wire 1 f out6 $end
$var wire 1 g out7 $end
$var wire 1 h out8 $end
$var wire 1 i out9 $end
$upscope $end
$upscope $end
$enddefinitions $end
#0
$dumpvars
0i
0h
0g
0f
0e
0d
0c
0b
0a
0`
0_
0^
0]
0\
0[
0Z
0Y
0X
0W
0V
0U
0T
0S
0R
0Q
0P
0O
0N
0M
0L
0K
0J
0I
0H
0G
0F
0E
0D
0C
0B
0A
0@
0?
0>
0=
0<
0;
0:
09
08
07
06
05
04
03
02
01
10
1/
1.
1-
1,
1+
1*
1)
0(
0'
0&
0%
0$
0#
0"
0!
$end
#40
0)
1!
#60
1)
0*
0!
1"
#80
11
1F
0)
1!
#100
01
0F
1)
1*
0+
0!
0"
1#
#120
11
1E
0)
1!
#140
1?
0E
1e
1)
0*
0!
1"
#160
0?
0)
1!
#180
01
0e
1)
1*
1+
0,
0!
0"
0#
1$
#200
11
1D
0)
1!
#220
1=
0D
1d
1)
0*
0!
1"
#240
0=
0)
1!
#260
1^
18
1`
0d
1)
1*
0+
0!
0"
1#
#280
08
0^
0)
1!
#300
1^
0`
1)
0*
0!
1"
#320
01
0^
0)
1!
#340
1)
1*
1+
1,
0-
0!
0"
0#
0$
1%
#360
11
1C
0)
1!
#380
1<
0C
1c
1)
0*
0!
1"
#400
0<
0)
1!
#420
1\
17
1]
0c
1)
1*
0+
0!
0"
1#
#440
07
0\
0)
1!
#460
1\
0]
1)
0*
0!
1"
#480
01
0\
0)
1!
#500
11
1U
1i
1V
1W
1)
1*
1+
0,
0!
0"
0#
1$
#520
0i
0U
0V
0)
1!
#540
1V
0W
1)
0*
0!
1"
#560
01
0V
0)
1!
#580
11
1U
1)
1*
0+
0!
0"
1#
#600
01
0U
0)
1!
#620
1)
0*
0!
1"
#640
0)
1!
#660
1)
1*
1+
1,
1-
0.
0!
0"
0#
0$
0%
1&
#680
11
1B
0)
1!
#700
1;
0B
1b
1)
0*
0!
1"
#720
0;
0)
1!
#740
1Z
16
1[
0b
1)
1*
0+
0!
0"
1#
#760
06
0Z
0)
1!
#780
1Z
0[
1)
0*
0!
1"
#800
01
0Z
0)
1!
#820
11
1Q
1h
1R
1S
1)
1*
1+
0,
0!
0"
0#
1$
#840
0h
0Q
0R
0)
1!
#860
1R
0S
1)
0*
0!
1"
#880
01
0R
0)
1!
#900
11
1Q
1)
1*
0+
0!
0"
1#
#920
01
0Q
0)
1!
#940
1)
0*
0!
1"
#960
0)
1!
#980
11
1_
1K
1L
1M
1)
1*
1+
1,
0-
0!
0"
0#
0$
1%
#1000
0_
0K
0L
0)
1!
#1020
1L
0M
1)
0*
0!
1"
#1040
01
0L
0)
1!
#1060
11
1K
1)
1*
0+
0!
0"
1#
#1080
01
0K
0)
1!
#1100
1)
0*
0!
1"
#1120
0)
1!
#1140
11
1_
1)
1*
1+
0,
0!
0"
0#
1$
#1160
01
0_
0)
1!
#1180
1)
0*
0!
1"
#1200
0)
1!
#1220
1)
1*
0+
0!
0"
1#
#1240
0)
1!
#1260
1)
0*
0!
1"
#1280
0)
1!
#1300
1)
1*
1+
1,
1-
1.
0/
0!
0"
0#
0$
0%
0&
1'
#1320
11
1A
0)
1!
#1340
1:
0A
1a
1)
0*
0!
1"
#1360
0:
0)
1!
#1380
1X
15
1Y
0a
1)
1*
0+
0!
0"
1#
#1400
05
0X
0)
1!
#1420
1X
0Y
1)
0*
0!
1"
#1440
01
0X
0)
1!
#1460
11
1N
1g
1O
1P
1)
1*
1+
0,
0!
0"
0#
1$
#1480
0g
0N
0O
0)
1!
#1500
1O
0P
1)
0*
0!
1"
#1520
01
0O
0)
1!
#1540
11
1N
1)
1*
0+
0!
0"
1#
#1560
01
0N
0)
1!
#1580
1)
0*
0!
1"
#1600
0)
1!
#1620
11
1T
1G
1H
1J
1)
1*
1+
1,
0-
0!
0"
0#
0$
1%
#1640
0T
0G
0H
0)
1!
#1660
1H
0J
1)
0*
0!
1"
#1680
01
0H
0)
1!
#1700
11
1G
1)
1*
0+
0!
0"
1#
#1720
01
0G
0)
1!
#1740
1)
0*
0!
1"
#1760
0)
1!
#1780
11
1T
1)
1*
1+
0,
0!
0"
0#
1$
#1800
01
0T
0)
1!
#1820
1)
0*
0!
1"
#1840
0)
1!
#1860
1)
1*
0+
0!
0"
1#
#1880
0)
1!
#1900
1)
0*
0!
1"
#1920
0)
1!
#1940
11
1>
1)
1*
1+
1,
1-
0.
0!
0"
0#
0$
0%
1&
#1960
0>
1A
0)
1!
#1980
1:
0A
1)
0*
0!
1"
#2000
01
0:
0)
1!
#2020
11
15
1)
1*
0+
0!
0"
1#
#2040
01
05
0)
1!
#2060
1)
0*
0!
1"
#2080
0)
1!
#2100
11
1g
1)
1*
1+
0,
0!
0"
0#
1$
#2120
01
0g
0)
1!
#2140
1)
0*
0!
1"
#2160
0)
1!
#2180
1)
1*
0+
0!
0"
1#
#2200
0)
1!
#2220
1)
0*
0!
1"
#2240
0)
1!
#2260
11
1>
1)
1*
1+
1,
0-
0!
0"
0#
0$
1%
#2280
01
0>
0)
1!
#2300
1)
0*
0!
1"
#2320
0)
1!
#2340
1)
1*
0+
0!
0"
1#
#2360
0)
1!
#2380
1)
0*
0!
1"
#2400
0)
1!
#2420
1)
1*
1+
0,
0!
0"
0#
1$
#2440
0)
1!
#2460
1)
0*
0!
1"
#2480
0)
1!
#2500
1)
1*
0+
0!
0"
1#
#2520
0)
1!
#2540
1)
0*
0!
1"
#2560
0)
1!
#2580
1)
1*
1+
1,
1-
1.
1/
00
0!
0"
0#
0$
0%
0&
0'
1(
#2600
11
1@
0)
1!
#2620
19
0@
1)
0*
0!
1"
#2640
09
1F
0)
1!
#2660
14
0F
1)
1*
0+
0!
0"
1#
#2680
04
1E
0)
1!
#2700
1?
0E
1)
0*
0!
1"
#2720
01
0?
0)
1!
#2740
11
1f
1)
1*
1+
0,
0!
0"
0#
1$
#2760
0f
1D
0)
1!
#2780
1=
0D
1)
0*
0!
1"
#2800
01
0=
0)
1!
#2820
11
18
1)
1*
0+
0!
0"
1#
#2840
01
08
0)
1!
#2860
1)
0*
0!
1"
#2880
0)
1!
#2900
11
1I
1)
1*
1+
1,
0-
0!
0"
0#
0$
1%
#2920
0I
1C
0)
1!
#2940
1<
0C
1)
0*
0!
1"
#2960
01
0<
0)
1!
#2980
11
17
1)
1*
0+
0!
0"
1#
#3000
01
07
0)
1!
#3020
1)
0*
0!
1"
#3040
0)
1!
#3060
11
1i
1)
1*
1+
0,
0!
0"
0#
1$
#3080
01
0i
0)
1!
#3100
1)
0*
0!
1"
#3120
0)
1!
#3140
1)
1*
0+
0!
0"
1#
#3160
0)
1!
#3180
1)
0*
0!
1"
#3200
0)
1!
#3220
11
13
1)
1*
1+
1,
1-
0.
0!
0"
0#
0$
0%
1&
#3240
03
1B
0)
1!
#3260
1;
0B
1)
0*
0!
1"
#3280
01
0;
0)
1!
#3300
11
16
1)
1*
0+
0!
0"
1#
#3320
01
06
0)
1!
#3340
1)
0*
0!
1"
#3360
0)
1!
#3380
11
1h
1)
1*
1+
0,
0!
0"
0#
1$
#3400
01
0h
0)
1!
#3420
1)
0*
0!
1"
#3440
0)
1!
#3460
1)
1*
0+
0!
0"
1#
#3480
0)
1!
#3500
1)
0*
0!
1"
#3520
0)
1!
#3540
11
13
1)
1*
1+
1,
0-
0!
0"
0#
0$
1%
#3560
01
03
0)
1!
#3580
1)
0*
0!
1"
#3600
0)
1!
#3620
1)
1*
0+
0!
0"
1#
#3640
0)
1!
#3660
1)
0*
0!
1"
#3680
0)
1!
#3700
1)
1*
1+
0,
0!
0"
0#
1$
#3720
0)
1!
#3740
1)
0*
0!
1"
#3760
0)
1!
#3780
1)
1*
0+
0!
0"
1#
#3800
0)
1!
#3820
1)
0*
0!
1"
#3840
0)
1!
#3860
11
12
1)
1*
1+
1,
1-
1.
0/
0!
0"
0#
0$
0%
0&
1'
#3880
02
1@
0)
1!
#3900
19
0@
1)
0*
0!
1"
#3920
01
09
0)
1!
#3940
11
14
1)
1*
0+
0!
0"
1#
#3960
01
04
0)
1!
#3980
1)
0*
0!
1"
#4000
0)
1!
#4020
11
1f
1)
1*
1+
0,
0!
0"
0#
1$
#4040
01
0f
0)
1!
#4060
1)
0*
0!
1"
#4080
0)
1!
#4100
1)
1*
0+
0!
0"
1#
#4120
0)
1!
#4140
1)
0*
0!
1"
#4160
0)
1!
#4180
11
1I
1)
1*
1+
1,
0-
0!
0"
0#
0$
1%
#4200
01
0I
0)
1!
#4220
1)
0*
0!
1"
#4240
0)
1!
#4260
1)
1*
0+
0!
0"
1#
#4280
0)
1!
#4300
1)
0*
0!
1"
#4320
0)
1!
#4340
1)
1*
1+
0,
0!
0"
0#
1$
#4360
0)
1!
#4380
1)
0*
0!
1"
#4400
0)
1!
#4420
1)
1*
0+
0!
0"
1#
#4440
0)
1!
#4460
1)
0*
0!
1"
#4480
0)
1!
#4500
11
12
1)
1*
1+
1,
1-
0.
0!
0"
0#
0$
0%
1&
#4520
01
02
0)
1!
#4540
1)
0*
0!
1"
#4560
0)
1!
#4580
1)
1*
0+
0!
0"
1#
#4600
0)
1!
#4620
1)
0*
0!
1"
#4640
0)
1!
#4660
1)
1*
1+
0,
0!
0"
0#
1$
#4680
0)
1!
#4700
1)
0*
0!
1"
#4720
0)
1!
#4740
1)
1*
0+
0!
0"
1#
#4760
0)
1!
#4780
1)
0*
0!
1"
#4800
0)
1!
#4820
1)
1*
1+
1,
0-
0!
0"
0#
0$
1%
#4840
0)
1!
#4860
1)
0*
0!
1"
#4880
0)
1!
#4900
1)
1*
0+
0!
0"
1#
#4920
0)
1!
#4940
1)
0*
0!
1"
#4960
0)
1!
#4980
1)
1*
1+
0,
0!
0"
0#
1$
#5000
0)
1!
#5020
1)
0*
0!
1"
#5040
0)
1!
#5060
1)
1*
0+
0!
0"
1#
#5080
0)
1!
#5100
1)
0*
0!
1"
