GOLPixel.v
module GOLPixel(out, a, b, c, d, e, f, g, h);

	output wire out;
	input wire a, b, c, d, e, f, g, h;
	
	not notA(nA, a);
	not notB(nB, b);
	not notC(nC, c);
	not notD(nD, d);
	not notE(nE, e);
	not notF(nF, f);
	not notG(nG, g);
	not notH(nH, h);
	
	and and0(out0, nA, nB, nC, nD, nE, g, h);
	and and1(out1, nA, nB, nC, nD, f, nG, h);
	and and2(out2, nA, nB, nC, nD, f, g, nH);
	and and3(out3, nA, nB, nC, nD, e, nF, h);
	and and4(out4, nA, nB, nC, e, nF, g, nH);
	and and5(out5, nA, nB, nC, e, f, nG, nH);
	and and6(out6, nA, nB, nC, d, nE, nF, h);
	and and7(out7, nA, nB, nC, d, nE, g, nH);
	and and8(out8, nA, nB, nC, d, nE, f, nG);
	and and9(out9, nA, nB, nC, d, e, nF, nG);
	and and10(out10, nA, nB, c, nD, nE, nF, h);
	and and11(out11, nA, nB, c, nD, nE, g, nH);
	and and12(out12, nA, nB, c, nD, nE, f, nG);
	and and13(out13, nA, nB, c, nD, e, nF, nG);
	and and14(out14, nA, nB, c, d, nE, nF, nG);
	and and15(out15, nA, b, nC, nD, nE, nF, h);
	and and16(out16, nA, b, nC, nD, nE, g, nH);
	and and17(out17, nA, b, nC, nD, nE, f, nG);
	and and18(out18, nA, b, nC, nD, e, nF, nG);
	and and19(out19, nA, b, nC, d, nE, nF, nG);
	and and20(out20, nA, b, c, nD, nE, nF, nG);
	and and21(out21, a, nB, nC, nD, nE, nF, h);
	and and22(out22, a, nB, nC, nD, nE, g, nH);
	and and23(out23, a, nB, nC, nD, nE, f, nG);
	and and24(out24, a, nB, nC, nD, e, nF, nG);
	and and25(out25, a, nB, nC, d, nE, nF, nG);
	and and26(out26, a, nB, c, nD, nE, nF, nG);
	and and27(out27, a, b, nC, nD, nE, nF, nG);
	and and28(out28, nA, nB, nD, e, nF, g, nH);
	and and29(out29, nA, nC, nD, e, nF, g, nH);
	and and30(out30, nB, nC, nD, e, nF, g, nH);
	and and31(out31, nA, nB, nD, e, f, nG, nH);
	and and32(out32, nA, nC, nD, e, f, nG, nH);
	and and33(out33, nB, nC, nD, e, f, nG, nH);
	and and34(out34, nA, nB, d, nE, nF, g, nH);
	and and35(out35, nA, nC, d, nE, nF, g, nH);
	and and36(out36, nB, nC, d, nE, nF, g, nH);
	and and37(out37, nA, nB, d, nE, f, nG, nH);
	and and38(out38, nA, nC, d, nE, f, nG, nH);
	and and39(out39, nB, nC, d, nE, f, nG, nH);
	and and40(out40, nA, nB, d, e, nF, nG, nH);
	and and41(out41, nA, nC, d, e, nF, nG, nH);
	and and42(out42, nB, nC, d, e, nF, nG, nH);
	and and43(out43, nA, c, nD, nE, nF, g, nH);
	and and44(out44, nB, c, nD, nE, nF, g, nH);
	and and45(out45, nA, c, nD, nE, f, nG, nH);
	and and46(out46, nB, c, nD, nE, f, nG, nH);
	and and47(out47, nA, c, nD, e, nF, nG, nH);
	and and48(out48, nB, c, nD, e, nF, nG, nH);
	and and49(out49, nA, c, d, nE, nF, nG, nH);
	and and50(out50, nB, c, d, nE, nF, nG, nH);
	and and51(out51, b, nC, nD, nE, nF, g, nH);
	and and52(out52, b, nC, nD, nE, f, nG, nH);
	and and53(out53, b, nC, nD, e, nF, nG, nH);
	and and54(out54, b, nC, d, nE, nF, nG, nH);
	and and55(out55, b, c, nD, nE, nF, nG, nH);

	or or0(out, out0, out1, out2, out3, out4, out5, out6, out7, 
	out8, out9, out10, out11, out12, out13, out14, out15, 
	out16, out17, out18, out19, out20, out21, out22, out23, 
	out24, out25, out26, out27, out28, out29, out30, out31, 
	out32, out33, out34, out35, out36, out37, out38, out39, 
	out40, out41, out42, out43, out44, out45, out46, out47, 
	out48, out49, out50, out51, out52, out53, out54, out55);

	
endmodule

GOLPixelTest.v
`include "GOLPixel.v"

module TestBench;

	GOLPixel pixel(out, a, b, c, d, e, f, g, h);
	Tester myTester(a, b, c, d, e, f, g, h, out);

	wire out;
	wire a, b, c, d, e, f, g, h;

	initial
	begin
		$dumpfile("pixel.vcd");
		$dumpvars(1,pixel);
	end

endmodule

module Tester(a, b, c, d, e, f, g, h, out);
	output wire a, b, c, d, e, f, g, h;
	input wire out;
	
	reg[7:0] outreg;
	
	reg[7:0] i;
	
	assign a = outreg[0];
	assign b = outreg[1];
	assign c = outreg[2];
	assign d = outreg[3];
	assign e = outreg[4];
	assign f = outreg[5];
	assign g = outreg[6];
	assign h = outreg[7];
	
	parameter delay = 20;
	
	initial
	begin
		outreg = 8'd0;
		i = 8'd0;
	end
	
	always
	begin
	repeat(255) begin
		#delay outreg = i;
		i = i+1;
	end
	$finish;
	end
endmodule

pixel2.vcd
$date
	Tue Nov 20 14:30:03 2012
$end
$version
	Icarus Verilog
$end
$timescale
	1s
$end
$scope module TestBench $end
$scope module pixel $end
$var wire 1 ! a $end
$var wire 1 " b $end
$var wire 1 # c $end
$var wire 1 $ d $end
$var wire 1 % e $end
$var wire 1 & f $end
$var wire 1 ' g $end
$var wire 1 ( h $end
$var wire 1 ) nA $end
$var wire 1 * nB $end
$var wire 1 + nC $end
$var wire 1 , nD $end
$var wire 1 - nE $end
$var wire 1 . nF $end
$var wire 1 / nG $end
$var wire 1 0 nH $end
$var wire 1 1 out $end
$var wire 1 2 out0 $end
$var wire 1 3 out1 $end
$var wire 1 4 out10 $end
$var wire 1 5 out11 $end
$var wire 1 6 out12 $end
$var wire 1 7 out13 $end
$var wire 1 8 out14 $end
$var wire 1 9 out15 $end
$var wire 1 : out16 $end
$var wire 1 ; out17 $end
$var wire 1 < out18 $end
$var wire 1 = out19 $end
$var wire 1 > out2 $end
$var wire 1 ? out20 $end
$var wire 1 @ out21 $end
$var wire 1 A out22 $end
$var wire 1 B out23 $end
$var wire 1 C out24 $end
$var wire 1 D out25 $end
$var wire 1 E out26 $end
$var wire 1 F out27 $end
$var wire 1 G out28 $end
$var wire 1 H out29 $end
$var wire 1 I out3 $end
$var wire 1 J out30 $end
$var wire 1 K out31 $end
$var wire 1 L out32 $end
$var wire 1 M out33 $end
$var wire 1 N out34 $end
$var wire 1 O out35 $end
$var wire 1 P out36 $end
$var wire 1 Q out37 $end
$var wire 1 R out38 $end
$var wire 1 S out39 $end
$var wire 1 T out4 $end
$var wire 1 U out40 $end
$var wire 1 V out41 $end
$var wire 1 W out42 $end
$var wire 1 X out43 $end
$var wire 1 Y out44 $end
$var wire 1 Z out45 $end
$var wire 1 [ out46 $end
$var wire 1 \ out47 $end
$var wire 1 ] out48 $end
$var wire 1 ^ out49 $end
$var wire 1 _ out5 $end
$var wire 1 ` out50 $end
$var wire 1 a out51 $end
$var wire 1 b out52 $end
$var wire 1 c out53 $end
$var wire 1 d out54 $end
$var wire 1 e out55 $end
$var wire 1 f out6 $end
$var wire 1 g out7 $end
$var wire 1 h out8 $end
$var wire 1 i out9 $end
$upscope $end
$upscope $end
$enddefinitions $end
#0
$dumpvars
0i
0h
0g
0f
0e
0d
0c
0b
0a
0`
0_
0^
0]
0\
0[
0Z
0Y
0X
0W
0V
0U
0T
0S
0R
0Q
0P
0O
0N
0M
0L
0K
0J
0I
0H
0G
0F
0E
0D
0C
0B
0A
0@
0?
0>
0=
0<
0;
0:
09
08
07
06
05
04
03
02
01
10
1/
1.
1-
1,
1+
1*
1)
0(
0'
0&
0%
0$
0#
0"
0!
$end
#20
11
1F
0)
0*
1!
1"
#40
1E
0F
1*
0+
0"
1#
#60
1?
0E
1e
1)
0*
0!
1"
#80
0?
0)
1!
#100
1D
0e
1*
1+
0,
0"
0#
1$
#120
1=
0D
1d
1)
0*
0!
1"
#140
0=
0)
1!
#160
1^
18
1`
0d
1)
1*
0+
0!
0"
1#
#180
08
0^
0)
1!
#200
1^
0`
1)
0*
0!
1"
#220
0^
1C
0)
1*
1+
1,
0-
1!
0"
0#
0$
1%
#240
1<
0C
1c
1)
0*
0!
1"
#260
0<
0)
1!
#280
1\
17
1]
0c
1)
1*
0+
0!
0"
1#
#300
07
0\
0)
1!
#320
1\
0]
1)
0*
0!
1"
#340
1U
1i
1V
1W
0\
1*
1+
0,
0"
0#
1$
#360
0i
0U
0V
0)
1!
#380
1V
0W
1)
0*
0!
1"
#400
1U
0V
1*
0+
0"
1#
#420
1B
0U
0)
1+
1,
1-
0.
1!
0#
0$
0%
1&
#440
1;
0B
1b
1)
0*
0!
1"
#460
0;
0)
1!
#480
1Z
16
1[
0b
1)
1*
0+
0!
0"
1#
#500
06
0Z
0)
1!
#520
1Z
0[
1)
0*
0!
1"
#540
1Q
1h
1R
1S
0Z
1*
1+
0,
0"
0#
1$
#560
0h
0Q
0R
0)
1!
#580
1R
0S
1)
0*
0!
1"
#600
1Q
0R
1*
0+
0"
1#
#620
1_
1K
1L
1M
0Q
1+
1,
0-
0#
0$
1%
#640
0_
0K
0L
0)
1!
#660
1L
0M
1)
0*
0!
1"
#680
1K
0L
1*
0+
0"
1#
#700
1_
0K
1+
0,
0#
1$
#720
1A
0_
0)
1,
1-
1.
0/
1!
0$
0%
0&
1'
#740
1:
0A
1a
1)
0*
0!
1"
#760
0:
0)
1!
#780
1X
15
1Y
0a
1)
1*
0+
0!
0"
1#
#800
05
0X
0)
1!
#820
1X
0Y
1)
0*
0!
1"
#840
1N
1g
1O
1P
0X
1*
1+
0,
0"
0#
1$
#860
0g
0N
0O
0)
1!
#880
1O
0P
1)
0*
0!
1"
#900
1N
0O
1*
0+
0"
1#
#920
1T
1G
1H
1J
0N
1+
1,
0-
0#
0$
1%
#940
0T
0G
0H
0)
1!
#960
1H
0J
1)
0*
0!
1"
#980
1G
0H
1*
0+
0"
1#
#1000
1T
0G
1+
0,
0#
1$
#1020
11
1>
0T
1,
1-
0.
0$
0%
1&
#1040
0>
1A
0)
1!
#1060
1:
0A
1)
0*
0!
1"
#1080
15
0:
1*
0+
0"
1#
#1100
1g
05
1+
0,
0#
1$
#1120
1>
0g
1,
0-
0$
1%
#1140
1@
0>
0)
1-
1.
1/
00
1!
0%
0&
0'
1(
#1160
19
0@
1)
0*
0!
1"
#1180
09
1F
0)
1!
#1200
14
0F
1)
1*
0+
0!
0"
1#
#1220
04
1E
0)
1!
#1240
1?
0E
1)
0*
0!
1"
#1260
1f
0?
1*
1+
0,
0"
0#
1$
#1280
0f
1D
0)
1!
#1300
1=
0D
1)
0*
0!
1"
#1320
18
0=
1*
0+
0"
1#
#1340
1I
08
1+
1,
0-
0#
0$
1%
#1360
0I
1C
0)
1!
#1380
1<
0C
1)
0*
0!
1"
#1400
17
0<
1*
0+
0"
1#
#1420
1i
07
1+
0,
0#
1$
#1440
11
13
0i
1,
1-
0.
0$
0%
1&
#1460
03
1B
0)
1!
#1480
1;
0B
1)
0*
0!
1"
#1500
16
0;
1*
0+
0"
1#
#1520
1h
06
1+
0,
0#
1$
#1540
13
0h
1,
0-
0$
1%
#1560
11
12
03
1-
1.
0/
0%
0&
1'
#1580
02
1@
0)
1!
#1600
19
0@
1)
0*
0!
1"
#1620
14
09
1*
0+
0"
1#
#1640
1f
04
1+
0,
0#
1$
#1660
1I
0f
1,
0-
0$
1%
#1680
12
0I
1-
0.
0%
1&
#1800
01
02
1.
1/
10
0&
0'
0(
#1820
0)
1!
#1840
1)
0*
0!
1"
#1860
1*
0+
0"
1#
#1880
1+
0,
0#
1$
#1900
01
0`
0^
08
0)
0*
0+
1!
1"
1#
#1920
1)
1*
1+
1,
0-
0!
0"
0#
0$
1%
#1940
01
0]
0\
07
0)
0*
0+
1!
1"
1#
#1960
1+
0,
0#
1$
#1980
1*
0+
0"
1#
#2000
1)
0*
0!
1"
#2020
0)
1!
#2040
1)
1*
1+
1,
1-
0.
0!
0"
0#
0$
0%
1&
#2060
01
0[
0Z
06
0)
0*
0+
1!
1"
1#
#2080
1+
0,
0#
1$
#2100
1*
0+
0"
1#
#2120
1)
0*
0!
1"
#2140
0)
1!
#2160
1+
1,
0-
0#
0$
1%
#2180
1*
0+
0"
1#
#2200
1)
0*
0!
1"
#2220
0)
1!
#2240
1*
1+
0,
0"
0#
1$
#2260
1)
0*
0!
1"
#2280
0)
1!
#2300
1)
1*
0+
0!
0"
1#
#2320
0)
1!
#2340
1)
0*
0!
1"
#2360
0)
1!
#2380
1)
1*
1+
1,
1-
1.
0/
0!
0"
0#
0$
0%
0&
1'
#2400
01
0Y
0X
05
0)
0*
0+
1!
1"
1#
#2420
1+
0,
0#
1$
#2440
1*
0+
0"
1#
#2460
1)
0*
0!
1"
#2480
0)
1!
#2500
1+
1,
0-
0#
0$
1%
#2520
1*
0+
0"
1#
#2540
1)
0*
0!
1"
#2560
0)
1!
#2580
1*
1+
0,
0"
0#
1$
#2600
1)
0*
0!
1"
#2620
0)
1!
#2640
1)
1*
0+
0!
0"
1#
#2660
0)
1!
#2680
1)
0*
0!
1"
#2700
0)
1!
#2720
1+
1,
1-
0.
0#
0$
0%
1&
#2740
1*
0+
0"
1#
#2760
1)
0*
0!
1"
#2780
0)
1!
#2800
1*
1+
0,
0"
0#
1$
#2820
1)
0*
0!
1"
#2840
0)
1!
#2860
1)
1*
0+
0!
0"
1#
#2880
0)
1!
#2900
1)
0*
0!
1"
#2920
0)
1!
#2940
1*
1+
1,
0-
0"
0#
0$
1%
#2960
1)
0*
0!
1"
#2980
0)
1!
#3000
1)
1*
0+
0!
0"
1#
#3020
0)
1!
#3040
1)
0*
0!
1"
#3060
0)
1!
#3080
1)
1*
1+
0,
0!
0"
0#
1$
#3100
0)
1!
#3120
1)
0*
0!
1"
#3140
0)
1!
#3160
1)
1*
0+
0!
0"
1#
#3180
0)
1!
#3200
1)
0*
0!
1"
#3220
0)
1!
#3240
1)
1*
1+
1,
1-
1.
1/
00
0!
0"
0#
0$
0%
0&
0'
1(
#3260
01
0E
0?
04
0)
0*
0+
1!
1"
1#
#3280
1+
0,
0#
1$
#3300
1*
0+
0"
1#
#3320
1)
0*
0!
1"
#3340
0)
1!
#3360
1+
1,
0-
0#
0$
1%
#3380
1*
0+
0"
1#
#3400
1)
0*
0!
1"
#3420
0)
1!
#3440
1*
1+
0,
0"
0#
1$
#3460
1)
0*
0!
1"
#3480
0)
1!
#3500
1)
1*
0+
0!
0"
1#
#3520
0)
1!
#3540
1)
0*
0!
1"
#3560
0)
1!
#3580
1+
1,
1-
0.
0#
0$
0%
1&
#3600
1*
0+
0"
1#
#3620
1)
0*
0!
1"
#3640
0)
1!
#3660
1*
1+
0,
0"
0#
1$
#3680
1)
0*
0!
1"
#3700
0)
1!
#3720
1)
1*
0+
0!
0"
1#
#3740
0)
1!
#3760
1)
0*
0!
1"
#3780
0)
1!
#3800
1*
1+
1,
0-
0"
0#
0$
1%
#3820
1)
0*
0!
1"
#3840
0)
1!
#3860
1)
1*
0+
0!
0"
1#
#3880
0)
1!
#3900
1)
0*
0!
1"
#3920
0)
1!
#3940
1)
1*
1+
0,
0!
0"
0#
1$
#3960
0)
1!
#3980
1)
0*
0!
1"
#4000
0)
1!
#4020
1)
1*
0+
0!
0"
1#
#4040
0)
1!
#4060
1)
0*
0!
1"
#4080
0)
1!
#4100
1+
1,
1-
1.
0/
0#
0$
0%
0&
1'
#4120
1*
0+
0"
1#
#4140
1)
0*
0!
1"
#4160
0)
1!
#4180
1*
1+
0,
0"
0#
1$
#4200
1)
0*
0!
1"
#4220
0)
1!
#4240
1)
1*
0+
0!
0"
1#
#4260
0)
1!
#4280
1)
0*
0!
1"
#4300
0)
1!
#4320
1*
1+
1,
0-
0"
0#
0$
1%
#4340
1)
0*
0!
1"
#4360
0)
1!
#4380
1)
1*
0+
0!
0"
1#
#4400
0)
1!
#4420
1)
0*
0!
1"
#4440
0)
1!
#4460
1)
1*
1+
0,
0!
0"
0#
1$
#4480
0)
1!
#4500
1)
0*
0!
1"
#4520
0)
1!
#4540
1)
1*
0+
0!
0"
1#
#4560
0)
1!
#4580
1)
0*
0!
1"
#4600
0)
1!
#4620
1*
1+
1,
1-
0.
0"
0#
0$
0%
1&
#4640
1)
0*
0!
1"
#4660
0)
1!
#4680
1)
1*
0+
0!
0"
1#
#4700
0)
1!
#4720
1)
0*
0!
1"
#4740
0)
1!
#4760
1)
1*
1+
0,
0!
0"
0#
1$
#4780
0)
1!
#4800
1)
0*
0!
1"
#4820
0)
1!
#4840
1)
1*
0+
0!
0"
1#
#4860
0)
1!
#4880
1)
0*
0!
1"
#4900
0)
1!
#4920
1)
1*
1+
1,
0-
0!
0"
0#
0$
1%
#4940
0)
1!
#4960
1)
0*
0!
1"
#4980
0)
1!
#5000
1)
1*
0+
0!
0"
1#
#5020
0)
1!
#5040
1)
0*
0!
1"
#5060
0)
1!
#5080
1)
1*
1+
0,
0!
0"
0#
1$
#5100
0)
1!
#5120
1)
0*
0!
1"
#5140
0)
1!
#5160
1)
1*
0+
0!
0"
1#
#5180
0)
1!
#5200
1)
0*
0!
1"
#5220
0)
1!
